[
    {
        "dataset" : "bio-diseasome",
        "4-1" : 1391.00,
        "4-2" : 923.00,
        "4-3" : 18536.00,
        "4-4" : 42.00,
        "4-5" : 26632.00,
        "4-6" : 18171.00,
        "5-1" : 142784.00,
        "5-10" : 8814.00,
        "5-11" : 21456.00,
        "5-12" : 588.00,
        "5-13" : 8.00,
        "5-14" : 763.00,
        "5-15" : 24337.00,
        "5-16" : 3131.00,
        "5-17" : 40.00,
        "5-18" : 35.00,
        "5-19" : 2413.00,
        "5-2" : 217410.00,
        "5-20" : 205.00,
        "5-21" : 1264.00,
        "5-3" : 48213.00,
        "5-4" : 148826.00,
        "5-5" : 56259.00,
        "5-6" : 71595.00,
        "5-7" : 1524.00,
        "5-8" : 73.00,
        "5-9" : 15819.00
    },
    {
        "dataset" : "bio-yeast",
        "4-1" : 39.00,
        "4-2" : 195.00,
        "4-3" : 2547.00,
        "4-4" : 139.00,
        "4-5" : 71905.00,
        "4-6" : 30908.00,
        "5-1" : 593525.00,
        "5-10" : 1364.00,
        "5-11" : 2036.00,
        "5-12" : 126.00,
        "5-13" : 51.00,
        "5-14" : 144.00,
        "5-15" : 321.00,
        "5-16" : 111.00,
        "5-17" : 41.00,
        "5-18" : 10.00,
        "5-19" : 74.00,
        "5-2" : 347727.00,
        "5-20" : 15.00,
        "5-21" : 8.00,
        "5-3" : 122686.00,
        "5-4" : 14760.00,
        "5-5" : 7052.00,
        "5-6" : 11724.00,
        "5-7" : 2942.00,
        "5-8" : 113.00,
        "5-9" : 150.00
    },
    {
        "dataset" : "bio-celegans",
        "4-1" : 2967.00,
        "4-2" : 36895.00,
        "4-3" : 362826.00,
        "4-4" : 4493.00,
        "4-5" : 2903688.000,
        "4-6" : 495214.00,
        "5-1" : 125406190.00,
        "5-10" : 720404.00,
        "5-11" : 3835133.00,
        "5-12" : 67163.00,
        "5-13" : 11573.00,
        "5-14" : 441718.00,
        "5-15" : 401361.00,
        "5-16" : 204105.00,
        "5-17" : 11919.00,
        "5-18" : 4768.00,
        "5-19" : 125264.00,
        "5-2" : 30481039.00,
        "5-20" : 16164.00,
        "5-21" : 1887.00,
        "5-3" : 2793982.00,
        "5-4" : 22610346.00,
        "5-5" : 1315492.00,
        "5-6" : 6260340.00,
        "5-7" : 523697.00,
        "5-8" : 11720.00,
        "5-9" : 329246.00
    },
    {
        "dataset" : "ca-Erdos992",
        "4-1" : 450.00,
        "4-2" : 5077.00,
        "4-3" : 89274.00,
        "4-4" : 1895.00,
        "4-5" : 1105102.00,
        "4-6" : 663966.00,
        "5-1" : 9532914.00,
        "5-10" : 117176.00,
        "5-11" : 222146.00,
        "5-12" : 10042.00,
        "5-13" : 1020.00,
        "5-14" : 9835.00,
        "5-15" : 31643.00,
        "5-16" : 11062.00,
        "5-17" : 1137.00,
        "5-18" : 289.00,
        "5-19" : 5363.00,
        "5-2" : 17630266.00,
        "5-20" : 892.00,
        "5-21" : 168.00,
        "5-3" : 5512783.00,
        "5-4" : 1250111.00,
        "5-5" : 550278.00,
        "5-6" : 1510495.00,
        "5-7" : 145714.00,
        "5-8" : 5914.00,
        "5-9" : 16383.00
    },
    {
        "dataset" : "ca-GrQc",
        "4-1" : 329087.00,
        "4-2" : 65654.00,
        "4-3" : 627918.00,
        "4-4" : 1115.00,
        "4-5" : 405528.00,
        "4-6" : 553195.00,
        "5-1" : 1885675.00,
        "5-10" : 543952.00,
        "5-11" : 831010.00,
        "5-12" : 23499.00,
        "5-13" : 165.00,
        "5-14" : 52665.00,
        "5-15" : 5603436.00,
        "5-16" : 100011.00,
        "5-17" : 1573.00,
        "5-18" : 851.00,
        "5-19" : 673795.00,
        "5-2" : 7691388.00,
        "5-20" : 291050.00,
        "5-21" : 2215423.00,
        "5-3" : 3568219.00,
        "5-4" : 4377682.00,
        "5-5" : 3699162.00,
        "5-6" : 3911884.00,
        "5-7" : 50656.00,
        "5-8" : 3358.00,
        "5-9" : 835114.00
    },
    {
        "dataset" : "ca-netscience",
        "4-1" : 631.00,
        "4-2" : 894.00,
        "4-3" : 8762.00,
        "4-4" : 7.00,
        "4-5" : 12739.00,
        "4-6" : 8632.00,
        "5-1" : 45769.00,
        "5-10" : 2826.00,
        "5-11" : 9345.00,
        "5-12" : 42.00,
        "5-13" : 0.00,
        "5-14" : 1092.00,
        "5-15" : 6696.00,
        "5-16" : 493.00,
        "5-17" : 5.00,
        "5-18" : 0.00,
        "5-19" : 1661.00,
        "5-2" : 70835.00,
        "5-20" : 177.00,
        "5-21" : 358.00,
        "5-3" : 19425.00,
        "5-4" : 41935.00,
        "5-5" : 18571.00,
        "5-6" : 20071.00,
        "5-7" : 162.00,
        "5-8" : 13.00,
        "5-9" : 4942.00
    },
    {
        "dataset" : "email-enron-only",
        "4-1" : 779.00,
        "4-2" : 2732.00,
        "4-3" : 14108.00,
        "4-4" : 648.00,
        "4-5" : 16854.00,
        "4-6" : 28592.00,
        "5-1" : 64251.00,
        "5-10" : 21550.00,
        "5-11" : 29857.00,
        "5-12" : 4482.00,
        "5-13" : 266.00,
        "5-14" : 1447.00,
        "5-15" : 9216.00,
        "5-16" : 6955.00,
        "5-17" : 865.00,
        "5-18" : 642.00,
        "5-19" : 3901.00,
        "5-2" : 239893.00,
        "5-20" : 1713.00,
        "5-21" : 519.00,
        "5-3" : 150317.00,
        "5-4" : 75980.00,
        "5-5" : 76279.00,
        "5-6" : 66747.00,
        "5-7" : 15555.00,
        "5-8" : 1456.00,
        "5-9" : 8454.00
    },
    {
        "dataset" : "email-univ",
        "4-1" : 3419.00,
        "4-2" : 20706.00,
        "4-3" : 216810.00,
        "4-4" : 12628.00,
        "4-5" : 546076.00,
        "4-6" : 1106002.00,
        "5-1" : 3378930.00,
        "5-10" : 496871.00,
        "5-11" : 608166.00,
        "5-12" : 117926.00,
        "5-13" : 10453.00,
        "5-14" : 20996.00,
        "5-15" : 147639.00,
        "5-16" : 84392.00,
        "5-17" : 15680.00,
        "5-18" : 4697.00,
        "5-19" : 32340.00,
        "5-2" : 21350017.00,
        "5-20" : 6742.00,
        "5-21" : 2063.00,
        "5-3" : 14323000.00,
        "5-4" : 2072463.00,
        "5-5" : 2749426.00,
        "5-6" : 2917428.00,
        "5-7" : 792042.00,
        "5-8" : 76309.00,
        "5-9" : 117042.00
    },
    {
        "dataset" : "email-EU",
        "4-1" : 66530.00,
        "4-2" : 785550.00,
        "4-3" : 20210320.00,
        "4-4" : 402805.00,
        "4-5" : 461076249.00,
        "4-6" : 162235537.00,
        "5-1" : 39317731637.00,
        "5-10" : 156440004.00,
        "5-11" : 280476469.00,
        "5-12" : 12333355.00,
        "5-13" : 1980412.00,
        "5-14" : 5403008.00,
        "5-15" : 39751691.00,
        "5-16" : 10936254.00,
        "5-17" : 1964074.00,
        "5-18" : 565925.00,
        "5-19" : 3649177.00,
        "5-2" : 34222353335.00,
        "5-20" : 554017.00,
        "5-21" : 67022.00,
        "5-3" : 5278092818.00,
        "5-4" : 2423677931.00,
        "5-5" : 489539489.00,
        "5-6" : 2630288731.00,
        "5-7" : 216072199.00,
        "5-8" : 5297774.00,
        "5-9" : 11161776.00
    },
    {
        "dataset" : "soc-wiki-Vote",
        "4-1" : 836.00,
        "4-2" : 10610.00,
        "4-3" : 123511.00,
        "4-4" : 6873.00,
        "4-5" : 513524.00,
        "4-6" : 466608.00,
        "5-1" : 7275659.00,
        "5-10" : 286753.00,
        "5-11" : 546613.00,
        "5-12" : 64351.00,
        "5-13" : 8084.00,
        "5-14" : 18897.00,
        "5-15" : 63087.00,
        "5-16" : 55716.00,
        "5-17" : 10296.00,
        "5-18" : 3265.00,
        "5-19" : 15305.00,
        "5-2" : 13073128.00,
        "5-20" : 2215.00,
        "5-21" : 179.00,
        "5-3" : 3930742.00,
        "5-4" : 2447604.00,
        "5-5" : 928747.00,
        "5-6" : 1994097.00,
        "5-7" : 489542.00,
        "5-8" : 25010.00,
        "5-9" : 68875.00
    },
    {
        "dataset" : "contact-high-school",
        "4-1" : 134700.00,
        "4-2" : 296874.00,
        "4-3" : 1357245.00,
        "4-4" : 78359.00,
        "4-5" : 855066.00,
        "4-6" : 2679538.00,
        "5-1" : 4283340.00,
        "5-10" : 7322294.00,
        "5-11" : 6768862.00,
        "5-12" : 2138159.00,
        "5-13" : 103642.00,
        "5-14" : 379274.00,
        "5-15" : 5339882.00,
        "5-16" : 1999779.00,
        "5-17" : 425330.00,
        "5-18" : 244200.00,
        "5-19" : 1710434.00,
        "5-2" : 50038002.00,
        "5-20" : 810562.00,
        "5-21" : 410028.00,
        "5-3" : 47567413.00,
        "5-4" : 10325847.00,
        "5-5" : 31868585.00,
        "5-6" : 15180864.00,
        "5-7" : 4754623.00,
        "5-8" : 674692.00,
        "5-9" : 1936319.00
    },
    {
        "dataset" : "contact-primary-school",
        "4-1" : 693906.00,
        "4-2" : 2529980.00,
        "4-3" : 7499261.00,
        "4-4" : 760419.00,
        "4-5" : 3167498.00,
        "4-6" : 9407396.00,
        "5-1" : 15700391.00,
        "5-10" : 88345433.00,
        "5-11" : 81766698.00,
        "5-12" : 37626194.00,
        "5-13" : 3064280.00,
        "5-14" : 8512928.00,
        "5-15" : 42956476.00,
        "5-16" : 49201884.00,
        "5-17" : 12260159.00,
        "5-18" : 6984144.00,
        "5-19" : 32429869.00,
        "5-2" : 191142834.00,
        "5-20" : 11760365.00,
        "5-21" : 2985971.00,
        "5-3" : 173059873.00,
        "5-4" : 69430244.00,
        "5-5" : 155048069.00,
        "5-6" : 124080314.00,
        "5-7" : 55075259.00,
        "5-8" : 8321360.00,
        "5-9" : 24466045.00
    },
    {
        "dataset" : "web-polblogs",
        "4-1" : 3359.00,
        "4-2" : 20325.00,
        "4-3" : 148958.00,
        "4-4" : 8489.00,
        "4-5" : 1038807.00,
        "4-6" : 349745.00,
        "5-1" : 31418344.00,
        "5-10" : 361870.00,
        "5-11" : 724359.00,
        "5-12" : 83556.00,
        "5-13" : 27800.00,
        "5-14" : 36832.00,
        "5-15" : 157504.00,
        "5-16" : 110359.00,
        "5-17" : 19997.00,
        "5-18" : 10441.00,
        "5-19" : 59482.00,
        "5-2" : 9660295.00,
        "5-20" : 16471.00,
        "5-21" : 3017.00,
        "5-3" : 2977599.00,
        "5-4" : 3193519.00,
        "5-5" : 821707.00,
        "5-6" : 1634564.00,
        "5-7" : 613841.00,
        "5-8" : 24703.00,
        "5-9" : 79587.00
    },
    {
        "dataset" : "web-edu",
        "4-1" : 40022.00,
        "4-2" : 4628.00,
        "4-3" : 186184.00,
        "4-4" : 18.00,
        "4-5" : 1334548.00,
        "4-6" : 434510.00,
        "5-1" : 18182186.00,
        "5-10" : 106283.00,
        "5-11" : 256498.00,
        "5-12" : 296.00,
        "5-13" : 1.00,
        "5-14" : 17601.00,
        "5-15" : 407483.00,
        "5-16" : 4320.00,
        "5-17" : 12.00,
        "5-18" : 6.00,
        "5-19" : 9231.00,
        "5-2" : 27150864.00,
        "5-20" : 400.00,
        "5-21" : 177650.00,
        "5-3" : 5017233.00,
        "5-4" : 3949020.00,
        "5-5" : 1039209.00,
        "5-6" : 991397.00,
        "5-7" : 1033.00,
        "5-8" : 7.00,
        "5-9" : 100487.00
    }

]